[
  {
    "importRunId": "src-6000::6-0",
    "caseImportId": "src-6000",
    "properties": {
      "Import Run ID": "src-6000::6-0",
      "Case Import ID": "src-6000",
      "Run": "TC50 (steps 1 to 15) / 6.0",
      "Person": "skip (AP)",
      "Build": "",
      "Issue(s)": "",
      "Test Run Label": "6.0",
      "Platform": "",
      "Status": "Done"
    }
  },
  {
    "importRunId": "src-6000::5-6",
    "caseImportId": "src-6000",
    "properties": {
      "Import Run ID": "src-6000::5-6",
      "Case Import ID": "src-6000",
      "Run": "TC50 (steps 1 to 15) / 5.6",
      "Person": "SKIP (JH)",
      "Build": "",
      "Issue(s)": "",
      "Test Run Label": "5.6",
      "Platform": "",
      "Status": "Done"
    }
  },
  {
    "importRunId": "src-6000::5-5",
    "caseImportId": "src-6000",
    "properties": {
      "Import Run ID": "src-6000::5-5",
      "Case Import ID": "src-6000",
      "Run": "TC50 (steps 1 to 15) / 5.5",
      "Person": "Colin",
      "Build": "5.5.3031",
      "Issue(s)": "",
      "Test Run Label": "5.5",
      "Platform": "",
      "Status": "Done",
      "date:Date:start": "2023-06-07"
    }
  },
  {
    "importRunId": "src-6000::5-4-betainternal",
    "caseImportId": "src-6000",
    "properties": {
      "Import Run ID": "src-6000::5-4-betainternal",
      "Case Import ID": "src-6000",
      "Run": "TC50 (steps 1 to 15) / 5.4 / BetaInternal",
      "Person": "Gordon",
      "Build": "5.4.3032",
      "Issue(s)": "",
      "Test Run Label": "5.4",
      "Platform": "BetaInternal",
      "Status": "Done"
    }
  },
  {
    "importRunId": "src-6000::5-3-betainternal",
    "caseImportId": "src-6000",
    "properties": {
      "Import Run ID": "src-6000::5-3-betainternal",
      "Case Import ID": "src-6000",
      "Run": "TC50 (steps 1 to 15) / 5.3 / BetaInternal",
      "Person": "Andrew",
      "Build": "5.3.3038",
      "Issue(s)": "",
      "Test Run Label": "5.3",
      "Platform": "BetaInternal",
      "Status": "Done"
    }
  }
]
