[
  {
    "importRunId": "src-4025::4-9-betainternal",
    "caseImportId": "src-4025",
    "properties": {
      "Import Run ID": "src-4025::4-9-betainternal",
      "Case Import ID": "src-4025",
      "Run": "TC316 / 4.9 / BetaInternal",
      "Person": "Colin",
      "Build": "4.9.3009",
      "Issue(s)": "BL-7522",
      "Test Run Label": "4.9",
      "Platform": "BetaInternal",
      "Status": "Done",
      "date:Date:start": "2020-09-18"
    }
  },
  {
    "importRunId": "src-4025::4-7-fx",
    "caseImportId": "src-4025",
    "properties": {
      "Import Run ID": "src-4025::4-7-fx",
      "Case Import ID": "src-4025",
      "Run": "TC316 / 4.7 / FX",
      "Person": "",
      "Build": "",
      "Issue(s)": "BL-7522",
      "Test Run Label": "4.7",
      "Platform": "FX"
    }
  },
  {
    "importRunId": "src-4025::4-6-windows",
    "caseImportId": "src-4025",
    "properties": {
      "Import Run ID": "src-4025::4-6-windows",
      "Case Import ID": "src-4025",
      "Run": "TC316 / 4.6 / Windows",
      "Person": "Colin",
      "Build": "4.6.3017",
      "Issue(s)": "BL-7522",
      "Test Run Label": "4.6",
      "Platform": "Windows",
      "Status": "Problems",
      "date:Date:start": "2019-08-13"
    }
  },
  {
    "importRunId": "src-tc317-r479::6-3",
    "caseImportId": "src-tc317-r479",
    "properties": {
      "Import Run ID": "src-tc317-r479::6-3",
      "Case Import ID": "src-tc317-r479",
      "Run": "TC317 / 6.3",
      "Person": "Colin",
      "Build": "6.3.3040",
      "Issue(s)": "",
      "Test Run Label": "6.3",
      "Platform": "",
      "Status": "Done",
      "date:Date:start": "2026-01-20"
    }
  },
  {
    "importRunId": "src-tc317-r479::6-0",
    "caseImportId": "src-tc317-r479",
    "properties": {
      "Import Run ID": "src-tc317-r479::6-0",
      "Case Import ID": "src-tc317-r479",
      "Run": "TC317 / 6.0",
      "Person": "skip (AP)",
      "Build": "",
      "Issue(s)": "",
      "Test Run Label": "6.0",
      "Platform": "",
      "Status": "Done"
    }
  }
]
