[
  {
    "importId": "src-tc252-steps-34-to-36-r643",
    "properties": {
      "Import ID": "src-tc252-steps-34-to-36-r643",
      "Test Case": "Import into a new book. Verify that your audio is still aligned to the segments you made.",
      "Case Code": "TC252  (steps 34 to 36)",
      "Steps": "--          Import into a new book. Verify that your audio is still aligned to the segments you made.",
      "Priority": "1",
      "Past Issues": ""
    }
  },
  {
    "importId": "src-tc252-steps-37-38-r644",
    "properties": {
      "Import ID": "src-tc252-steps-37-38-r644",
      "Test Case": "Close the Talking Book tool. The segments should disappear.",
      "Case Code": "TC252  (steps 37 ,38)",
      "Steps": "--          Close the Talking Book tool. The segments should disappear.",
      "Priority": "1",
      "Past Issues": ""
    }
  },
  {
    "importId": "src-tc253-steps-1-to-47-r645",
    "properties": {
      "Import ID": "src-tc253-steps-1-to-47-r645",
      "Test Case": "Inline Formatting: Create a new page, enter some text. Select some words and give them color. Other words should have italics, etc. Everthing that we let you do with selected text. For some segment of text, apply all of that formatting to the same segment. Record the text. Now export the book and import into a blank book. -- Verify that the text has all the same formatting in Excel",
      "Case Code": "TC253 (steps 1 to 47)",
      "Steps": "Inline Formatting: Create a new page, enter some text. Select some words and give them color. Other words should have italics, etc. Everthing that we let you do with selected text. For some segment of text, apply all of that formatting to the same segment. Record the text.\nNow export the book and import into a blank book.\n--           Verify that the text has all the same formatting in Excel",
      "Priority": "1",
      "Past Issues": "BL-12435"
    }
  },
  {
    "importId": "src-tc253-48-to-51-r646",
    "properties": {
      "Import ID": "src-tc253-48-to-51-r646",
      "Test Case": "Now import into a blank book. Verify that all of the formatting was round-tripped correctly.",
      "Case Code": "TC253 (48 to 51)",
      "Steps": "--           Now import into a blank book. Verify that all of the formatting was round-tripped correctly.",
      "Priority": "1",
      "Past Issues": "BL-12435"
    }
  },
  {
    "importId": "src-tc56-import-origina-book-tc254-r647",
    "properties": {
      "Import ID": "src-tc56-import-origina-book-tc254-r647",
      "Test Case": "Export a book. Remove some pages from the spreadsheet. Now import back onto the original book and verify that they have been removed from the spreadsheet",
      "Case Code": "TC56 (import origina book) , TC254",
      "Steps": "Export a book. Remove some pages from the spreadsheet. Now import back onto the original book and verify that they have been removed from the spreadsheet",
      "Priority": "1",
      "Past Issues": ""
    }
  }
]
